odoo/addons/shopinvader_es_product_categ/README.rst
odoo/addons/shopinvader_es_product_categ/__init__.py
odoo/addons/shopinvader_es_product_categ/__manifest__.py
odoo/addons/shopinvader_es_product_categ/i18n/shopinvader_es_product_categ.pot
odoo/addons/shopinvader_es_product_categ/readme/CONTRIBUTORS.rst
odoo/addons/shopinvader_es_product_categ/readme/DESCRIPTION.rst
odoo/addons/shopinvader_es_product_categ/schemas/__init__.py
odoo/addons/shopinvader_es_product_categ/schemas/hierarchical_category.py
odoo/addons/shopinvader_es_product_categ/schemas/product_product.py
odoo/addons/shopinvader_es_product_categ/static/description/index.html
odoo/addons/shopinvader_es_product_categ/tests/__init__.py
odoo/addons/shopinvader_es_product_categ/tests/test_product_product.py
odoo/addons/shopinvader_es_product_categ/views/product_brand_view.xml
odoo_addon_shopinvader_es_product_categ-16.0.1.0.0.1.dist-info/METADATA
odoo_addon_shopinvader_es_product_categ-16.0.1.0.0.1.dist-info/WHEEL
odoo_addon_shopinvader_es_product_categ-16.0.1.0.0.1.dist-info/top_level.txt
odoo_addon_shopinvader_es_product_categ-16.0.1.0.0.1.dist-info/RECORD
